MultiprocessingSpider/__init__.py
MultiprocessingSpider/utils.py
MultiprocessingSpider/packages/__init__.py
MultiprocessingSpider/packages/packages.py
MultiprocessingSpider/spiders/__init__.py
MultiprocessingSpider/spiders/spiders.py
MultiprocessingSpider-1.1.2.dist-info/LICENSE.md
MultiprocessingSpider-1.1.2.dist-info/METADATA
MultiprocessingSpider-1.1.2.dist-info/WHEEL
MultiprocessingSpider-1.1.2.dist-info/top_level.txt
MultiprocessingSpider-1.1.2.dist-info/RECORD
