Metadata-Version: 2.1
Name: MultiprocessingSpider
Version: 1.1.2
Summary: A multiprocessing web crawling and web scraping framework.
Home-page: https://github.com/Xpp521/MultiprocessingSpider
Author: Xpp
Author-email: Xpp233@foxmail.com
License: GPLv3
Project-URL: Source, https://github.com/Xpp521/MultiprocessingSpider
Project-URL: Tracker, https://github.com/Xpp521/MultiprocessingSpider/issues
Project-URL: Documentation, https://github.com/Xpp521/MultiprocessingSpider/wiki
Keywords: crawler,spider,requests,multiprocessing
Platform: UNKNOWN
Classifier: Environment :: Console
Classifier: Development Status :: 5 - Production/Stable
Classifier: Operating System :: OS Independent
Classifier: Operating System :: MacOS :: MacOS X
Classifier: Operating System :: Microsoft :: Windows :: Windows NT/2000
Classifier: Operating System :: POSIX
Classifier: License :: OSI Approved :: GNU General Public License v3 (GPLv3)
Classifier: Intended Audience :: Developers
Classifier: Programming Language :: Python
Classifier: Programming Language :: Python :: 3
Classifier: Programming Language :: Python :: 3.4
Classifier: Programming Language :: Python :: 3.5
Classifier: Programming Language :: Python :: 3.6
Classifier: Programming Language :: Python :: 3.7
Classifier: Programming Language :: Python :: 3.8
Classifier: Programming Language :: Python :: 3.9
Classifier: Topic :: Internet :: WWW/HTTP
Classifier: Topic :: Software Development :: Libraries :: Application Frameworks
Classifier: Topic :: Software Development :: Libraries :: Python Modules
Requires-Python: >=3
Requires-Dist: requests
